spiops/.DS_Store
spiops/__init__.py
spiops/__init__.pyc
spiops/spiops.py
spiops/spiops.pyc
spiops/__pycache__/__init__.cpython-35.pyc
spiops/__pycache__/__init__.cpython-36.pyc
spiops/__pycache__/spiops.cpython-35.pyc
spiops/__pycache__/spiops.cpython-36.pyc
spiops/classes/__init__.py
spiops/classes/body.py
spiops/classes/data.py
spiops/classes/observation.py
spiops/classes/sensor.py
spiops/classes/__pycache__/__init__.cpython-35.pyc
spiops/classes/__pycache__/__init__.cpython-36.pyc
spiops/classes/__pycache__/body.cpython-35.pyc
spiops/classes/__pycache__/body.cpython-36.pyc
spiops/classes/__pycache__/data.cpython-35.pyc
spiops/classes/__pycache__/data.cpython-36.pyc
spiops/classes/__pycache__/observation.cpython-35.pyc
spiops/classes/__pycache__/observation.cpython-36.pyc
spiops/classes/__pycache__/sensor.cpython-35.pyc
spiops/classes/__pycache__/sensor.cpython-36.pyc
spiops/data/Mars_Viking_MDIM21_ClrMosaic_global_1024.jpg
spiops/data/Mars_Viking_MDIM21_ClrMosaic_global_1024.py
spiops/data/__init__.py
spiops/test/__init__.py
spiops/test/em16_spival.py
spiops/test/mex_spival.py
spiops/test/sandbox.py
spiops/test/siding_spring.py
spiops/test/test_functions.py
spiops/test/test_naif.py
spiops/utils/__init__.py
spiops/utils/naif.py
spiops/utils/time.py
spiops/utils/utils.py
spiops/utils/__pycache__/__init__.cpython-35.pyc
spiops/utils/__pycache__/__init__.cpython-36.pyc
spiops/utils/__pycache__/naif.cpython-36.pyc
spiops/utils/__pycache__/time.cpython-35.pyc
spiops/utils/__pycache__/time.cpython-36.pyc
spiops/utils/__pycache__/utils.cpython-35.pyc
spiops/utils/__pycache__/utils.cpython-36.pyc
spiops-0.4.4.data/data/LICENSE
spiops-0.4.4.data/scripts/spiops-mk
spiops-0.4.4.dist-info/METADATA
spiops-0.4.4.dist-info/RECORD
spiops-0.4.4.dist-info/WHEEL
spiops-0.4.4.dist-info/top_level.txt
