Metadata-Version: 2.1
Name: spiops
Version: 0.4.4
Summary: Extension of SPICE functionalities for ESA Planetary Missons
Home-page: https://github.com/esaSPICEservice/spiops
Author: Marc Costa Sitja
Author-email: marc.costa@esa.int
License: MIT License
Requires-Dist: spiceypy (>=2.0.0)
Requires-Dist: bokeh (>=0.12.15)
Requires-Dist: numpy (>=1.14.2)
Requires-Dist: matplotlib (>=2.2.2)
